tls_scan.py
tls_scan-0.1.7.dist-info/METADATA
tls_scan-0.1.7.dist-info/WHEEL
tls_scan-0.1.7.dist-info/entry_points.txt
tls_scan-0.1.7.dist-info/RECORD
