Metadata-Version: 2.1
Name: tls-scan
Version: 0.1.7
Summary: Scan IP addresses for TLS/SSL certificates
Home-page: https://github.com/s3rgeym/tls-scan
Author: Sergey M
Requires-Python: >=3.11,<4.0
Classifier: Programming Language :: Python :: 3
Classifier: Programming Language :: Python :: 3.11
Project-URL: Repository, https://github.com/s3rgeym/tls-scan
